pydspace/__init__.py
pydspace/conversion.py
pydspace/pydspace.py
pydspace/threads.py
pydspace/utils.py
pydspace-0.1.dist-info/LICENSE
pydspace-0.1.dist-info/METADATA
pydspace-0.1.dist-info/WHEEL
pydspace-0.1.dist-info/top_level.txt
pydspace-0.1.dist-info/RECORD
