Metadata-Version: 2.1
Name: pydspace
Version: 0.1
Summary: Python interface to operate with dspace.
Author: Kevin Lopez, Lucas Pompe
Author-email: kevinlopezandrade@gmail.com
Requires-Python: >=3.6
License-File: LICENSE
Requires-Dist: numpy
Requires-Dist: matlabengineforpython
